stdrun/__init__.py
stdrun/__main__.py
stdrun/process.py
stdrun/readline.py
stdrun/version.py
tests/test_version.py
stdrun-0.0.4.dist-info/LICENSE
stdrun-0.0.4.dist-info/METADATA
stdrun-0.0.4.dist-info/WHEEL
stdrun-0.0.4.dist-info/entry_points.txt
stdrun-0.0.4.dist-info/top_level.txt
stdrun-0.0.4.dist-info/RECORD
