Metadata-Version: 2.1
Name: stdrun
Version: 0.0.4
Summary: Python library and utility to handle process standard output and errors
Home-page: https://github.com/joaompinto/stdrun
Author: João Pinto
Author-email: lamego.pinto@gmail.com
License: MIT
License-File: LICENSE
Requires-Dist: colorama
